flac2all_pkg/__init__.py
flac2all_pkg/aac.py
flac2all_pkg/ccons.py
flac2all_pkg/config.py
flac2all_pkg/core.py
flac2all_pkg/ffmpeg.py
flac2all_pkg/flac.py
flac2all_pkg/flac2all_worker.py
flac2all_pkg/logging.py
flac2all_pkg/mp3.py
flac2all_pkg/opus.py
flac2all_pkg/shell.py
flac2all_pkg/termcolor.py
flac2all_pkg/vorbis.py
flac2all-5.4.dist-info/LICENCE
flac2all-5.4.dist-info/METADATA
flac2all-5.4.dist-info/WHEEL
flac2all-5.4.dist-info/entry_points.txt
flac2all-5.4.dist-info/top_level.txt
flac2all-5.4.dist-info/RECORD
