Metadata-Version: 2.1
Name: flac2all
Version: 5.4
Summary: Multi process, clustered, FLAC to multi codec audio converter with tagging support
Home-page: https://github.com/ZivaVatra/flac2all
Author: ZivaVatra
Author-email: info@ziva-vatra.com
License: GPLv3
Keywords: multithread,multiprocess,batch,flac,converter,mp3,vorbis,opus,aac,lame,music,audio,ffmpeg,cluster
Classifier: Development Status :: 5 - Production/Stable
Classifier: Environment :: Console
Classifier: Intended Audience :: End Users/Desktop
Classifier: License :: OSI Approved :: GNU Lesser General Public License v3 (LGPLv3)
Classifier: Natural Language :: English
Classifier: Operating System :: POSIX :: BSD
Classifier: Operating System :: POSIX :: Linux
Classifier: Programming Language :: Python :: 3.6
Classifier: Topic :: Multimedia :: Sound/Audio :: Conversion
License-File: LICENCE
Requires-Dist: pyzmq
